sisaws/__init__.py
sisaws-2.1.6.dist-info/METADATA
sisaws-2.1.6.dist-info/WHEEL
sisaws-2.1.6.dist-info/top_level.txt
sisaws-2.1.6.dist-info/RECORD
