Metadata-Version: 2.4
Name: sisaws
Version: 2.1.6
Summary: Librería oficial para interactuar con la API REST del SISA.
Author-email: Conde <billordowiyi@gmail.com>
Keywords: security,api,requests
Classifier: Programming Language :: Python :: 3
Classifier: Operating System :: OS Independent
Classifier: License :: OSI Approved :: MIT License
Requires-Python: >=3.6
Requires-Dist: requests>=2.0
